source/__init__.py
source/config.py
source/constants.py
source/utilities.py
source/gcal_sync/__init__.py
source/gcal_sync/call_sync.py
source/gcal_sync/get_events.py
source/gcal_sync/schemas.py
source/noko_logger/__init__.py
source/noko_logger/time_logger.py
source/setup/__init__.py
source/setup/setup.py
noko_cli-0.1.5.dist-info/METADATA
noko_cli-0.1.5.dist-info/WHEEL
noko_cli-0.1.5.dist-info/entry_points.txt
noko_cli-0.1.5.dist-info/top_level.txt
noko_cli-0.1.5.dist-info/RECORD
