Metadata-Version: 2.1
Name: noko_cli
Version: 0.1.5
Summary: A simple CLI interface for Noko time tracking.
Requires-Dist: click
Requires-Dist: python-freckle-client
Requires-Dist: python-dotenv
